pynamodb_factories/__init__.py
pynamodb_factories/exceptions.py
pynamodb_factories/factory.py
pynamodb_factories/fields.py
pynamodb_factories-0.1.3.dist-info/LICENSE.md
pynamodb_factories-0.1.3.dist-info/WHEEL
pynamodb_factories-0.1.3.dist-info/METADATA
pynamodb_factories-0.1.3.dist-info/RECORD
